{
 "type":"animals",
 "pronunciations": [
    {
     "value":"alligator",
     "image_url":"http://json-feed.junrhy.com/images/animals/alligator.jpg",
     "sound_url":"https://ssl.gstatic.com/dictionary/static/sounds/oxford/aligator--_us_1.mp3"
    },  
    {
     "value":"bear",
     "image_url":"http://json-feed.junrhy.com/images/animals/bear.jpg",
     "sound_url":"https://ssl.gstatic.com/dictionary/static/sounds/oxford/bear--_us_1.mp3"
    },
    {
     "value":"cat",
     "image_url":"http://json-feed.junrhy.com/images/animals/cat.jpg",
     "sound_url":"https://ssl.gstatic.com/dictionary/static/sounds/oxford/cat--_us_1.mp3"
    },
    {
     "value":"dog",
     "image_url":"http://json-feed.junrhy.com/images/animals/dog.jpg",
     "sound_url":"https://ssl.gstatic.com/dictionary/static/sounds/oxford/dog--_us_1.mp3"
    },
    {
     "value":"elephant",
     "image_url":"http://json-feed.junrhy.com/images/animals/elephant.jpg",
     "sound_url":"https://ssl.gstatic.com/dictionary/static/sounds/oxford/elephant--_us_1.mp3"
    },
    {
     "value":"flamingo",
     "image_url":"http://json-feed.junrhy.com/images/animals/flamingo.jpg",
     "sound_url":"https://ssl.gstatic.com/dictionary/static/sounds/oxford/flamingo--_us_1.mp3"
    },
    {
     "value":"giraffe",
     "image_url":"http://json-feed.junrhy.com/images/animals/giraffe.jpg",
     "sound_url":"https://ssl.gstatic.com/dictionary/static/sounds/oxford/giraffe--_us_1.mp3"
    },
    {
     "value":"horse",
     "image_url":"http://json-feed.junrhy.com/images/animals/horse.jpg",
     "sound_url":"https://ssl.gstatic.com/dictionary/static/sounds/oxford/horse--_us_1.mp3"
    },
    {
     "value":"iguana",
     "image_url":"http://json-feed.junrhy.com/images/animals/iguana.jpg",
     "sound_url":"https://ssl.gstatic.com/dictionary/static/sounds/oxford/iguana--_us_1.mp3"
    },
    {
     "value":"jellyfish",
     "image_url":"http://json-feed.junrhy.com/images/animals/jellyfish.jpg",
     "sound_url":"https://ssl.gstatic.com/dictionary/static/sounds/oxford/jellyfish--_us_1.mp3"
    },
    {
     "value":"kangaroo",
     "image_url":"http://json-feed.junrhy.com/images/animals/kangaroo.jpg",
     "sound_url":"https://ssl.gstatic.com/dictionary/static/sounds/oxford/kangaroo--_us_1.mp3"
    },
    {
     "value":"lion",
     "image_url":"http://json-feed.junrhy.com/images/animals/lion.jpg",
     "sound_url":"https://ssl.gstatic.com/dictionary/static/sounds/oxford/lion--_us_1.mp3"
    },
    {
     "value":"monkey",
     "image_url":"http://json-feed.junrhy.com/images/animals/monkey.jpg",
     "sound_url":"https://ssl.gstatic.com/dictionary/static/sounds/oxford/monkey--_us_1.mp3"
    },
    {
     "value":"narwhal",
     "image_url":"http://json-feed.junrhy.com/images/animals/narwhal.jpg",
     "sound_url":"https://ssl.gstatic.com/dictionary/static/sounds/oxford/narwhal--_us_1.mp3"
    },
    {
     "value":"owl",
     "image_url":"http://json-feed.junrhy.com/images/animals/owl.jpg",
     "sound_url":"https://ssl.gstatic.com/dictionary/static/sounds/oxford/owl--_us_1.mp3"
    },
    {
     "value":"panda",
     "image_url":"http://json-feed.junrhy.com/images/animals/panda.jpg",
     "sound_url":"https://ssl.gstatic.com/dictionary/static/sounds/oxford/panda--_us_1.mp3"
    },
    {
     "value":"",
     "image_url":"http://json-feed.junrhy.com/images/animals/raccoon.jpg",
     "sound_url":"https://ssl.gstatic.com/dictionary/static/sounds/oxford/raccoon--_us_1.mp3"
    },
    {
     "value":"",
     "image_url":"http://json-feed.junrhy.com/images/animals/squirrel.jpg",
     "sound_url":"https://ssl.gstatic.com/dictionary/static/sounds/oxford/squirrel--_us_1.mp3"
    },
    {
     "value":"",
     "image_url":"http://json-feed.junrhy.com/images/animals/tiger.jpg",
     "sound_url":"https://ssl.gstatic.com/dictionary/static/sounds/oxford/tiger--_us_1.mp3"
    },
    {
     "value":"unicorn",
     "image_url":"http://json-feed.junrhy.com/images/animals/unicorn.jpg",
     "sound_url":"https://ssl.gstatic.com/dictionary/static/sounds/oxford/unicorn--_us_1.mp3"
    },
    {
     "value":"vampire bat",
     "image_url":"http://json-feed.junrhy.com/images/animals/vampire bat.jpg",
     "sound_url":"https://ssl.gstatic.com/dictionary/static/sounds/oxford/vampirebat--_us_1.mp3"
    },
    {
     "value":"",
     "image_url":"http://json-feed.junrhy.com/images/animals/worm.jpg",
     "sound_url":"https://ssl.gstatic.com/dictionary/static/sounds/oxford/worm--_us_1.mp3"
    },
    {
     "value":"xenarthra",
     "image_url":"http://json-feed.junrhy.com/images/animals/xenarthra.jpg",
     "sound_url":"https://ssl.gstatic.com/dictionary/static/sounds/oxford/xenarthra--_us_1.mp3"
    },
    {
     "value":"",
     "image_url":"http://json-feed.junrhy.com/images/animals/yak.jpg",
     "sound_url":"https://ssl.gstatic.com/dictionary/static/sounds/oxford/yak--_us_1.mp3"
    },
    {
     "value":"",
     "image_url":"http://json-feed.junrhy.com/images/animals/zebra.jpg",
     "sound_url":"https://ssl.gstatic.com/dictionary/static/sounds/oxford/zebra--_us_1.mp3"
    }
  ]
}